{
  "crop": [
    0,
    0,
    0,
    0
  ],
  "done": {
    "variables": {
      "gameover": {
        "op": "greater-or-equal",
        "reference": 1
      }
    }
  },
  "reward": {
    "variables": {
      "row19_0": {
        "measurement": "absolute",
        "op": "less-than",
        "reference": 5,
        "reward": 0.05
      },
      "row19_1": {
        "measurement": "absolute",
        "op": "less-than",
        "reference": 5,
        "reward": 0.05
      },
      "row19_2": {
        "measurement": "absolute",
        "op": "less-than",
        "reference": 5,
        "reward": 0.05
      },
      "row19_3": {
        "measurement": "absolute",
        "op": "less-than",
        "reference": 5,
        "reward": 0.05
      },
      "row19_4": {
        "measurement": "absolute",
        "op": "less-than",
        "reference": 5,
        "reward": 0.05
      },
      "row19_5": {
        "measurement": "absolute",
        "op": "less-than",
        "reference": 5,
        "reward": 0.05
      },
      "row19_6": {
        "measurement": "absolute",
        "op": "less-than",
        "reference": 5,
        "reward": 0.05
      },
      "row19_7": {
        "measurement": "absolute",
        "op": "less-than",
        "reference": 5,
        "reward": 0.05
      },
      "row19_8": {
        "measurement": "absolute",
        "op": "less-than",
        "reference": 5,
        "reward": 0.05
      },
      "row19_9": {
        "measurement": "absolute",
        "op": "less-than",
        "reference": 5,
        "reward": 0.05
      },
      "score": {
        "reward": 0.02
      }
    }
  }
}
